MANIFEST.in
README.md
pyproject.toml
setup.py
amuse_galactics.egg-info/PKG-INFO
amuse_galactics.egg-info/SOURCES.txt
amuse_galactics.egg-info/dependency_links.txt
amuse_galactics.egg-info/requires.txt
amuse_galactics.egg-info/top_level.txt
src/amuse/community/galactics/Makefile
src/amuse/community/galactics/__init__.py
src/amuse/community/galactics/_version.py
src/amuse/community/galactics/gas_interface.py
src/amuse/community/galactics/interface.py
src/amuse/community/galactics/gas_src/src/Makefile
src/amuse/community/galactics/gas_src/src/alldens.f
src/amuse/community/galactics/gas_src/src/appdiskdens.f
src/amuse/community/galactics/gas_src/src/appdiskforce.f
src/amuse/community/galactics/gas_src/src/appdiskpot.f
src/amuse/community/galactics/gas_src/src/bessj01.f
src/amuse/community/galactics/gas_src/src/bulgedens.f
src/amuse/community/galactics/gas_src/src/bulgedenspsi.f
src/amuse/community/galactics/gas_src/src/bulgepotential.f
src/amuse/community/galactics/gas_src/src/contourden.f
src/amuse/community/galactics/gas_src/src/dbh.f
src/amuse/community/galactics/gas_src/src/dbhplot.f
src/amuse/community/galactics/gas_src/src/dens.f
src/amuse/community/galactics/gas_src/src/densrpsi.f
src/amuse/community/galactics/gas_src/src/diskdens.f
src/amuse/community/galactics/gas_src/src/diskdensf.f
src/amuse/community/galactics/gas_src/src/diskdenspsi.f
src/amuse/community/galactics/gas_src/src/diskdf.f
src/amuse/community/galactics/gas_src/src/diskdf3ez.f
src/amuse/community/galactics/gas_src/src/diskdf3intez.f
src/amuse/community/galactics/gas_src/src/diskdf5ez.f
src/amuse/community/galactics/gas_src/src/diskdf5intez.f
src/amuse/community/galactics/gas_src/src/diskinfo.f
src/amuse/community/galactics/gas_src/src/erfcc.f
src/amuse/community/galactics/gas_src/src/erfcen.f
src/amuse/community/galactics/gas_src/src/fixedbulgepot.f
src/amuse/community/galactics/gas_src/src/fixedhalopot.f
src/amuse/community/galactics/gas_src/src/flatdiskpot.cc
src/amuse/community/galactics/gas_src/src/fnamidden.f
src/amuse/community/galactics/gas_src/src/force.f
src/amuse/community/galactics/gas_src/src/gasdisk3.f90
src/amuse/community/galactics/gas_src/src/genbulge.c
